MANIFEST.in
README.rst
setup.cfg
setup.py
rcpy/__init__.py
rcpy/button.py
rcpy/clock.py
rcpy/encoder.py
rcpy/gpio.py
rcpy/led.py
rcpy/motor.py
rcpy/mpu9250.py
rcpy/servo.py
rcpy.egg-info/PKG-INFO
rcpy.egg-info/SOURCES.txt
rcpy.egg-info/dependency_links.txt
rcpy.egg-info/top_level.txt
src/_encoder.c
src/_gpio.c
src/_gpio_mmap.c
src/_motor.c
src/_mpu9250.c
src/_rcpy.c
src/_servo.c
test/__init__.py
test/test_clock.py
test/test_encoder.py
test/test_led.py
test/test_motor.py
test/test_mpu9250.py
test/test_rcpy.py