Metadata-Version: 1.2
Name: rcpy
Version: 0.4.0
Summary: Python Library for Robotics Cape on Beaglebone Black and Beaglebone Blue
Home-page: https://github.com/mcdeoliveira/rcpy
Author: Mauricio C. de Oliveira
Author-email: mauricio@ucsd.edu
License: MIT
Download-URL: https://github.com/mcdeoliveira/rcpy/archive/0.4.tar.gz
Keywords: Robotics Cape,Beaglebone Black,Beaglebone Blue
Platform: UNKNOWN
Classifier: Development Status :: 3 - Alpha
Classifier: Intended Audience :: Other Audience
Classifier: Topic :: Scientific/Engineering
Classifier: License :: OSI Approved :: MIT License
Classifier: Programming Language :: Python :: 3.4
Requires-Python: >=3.4
